Practical-4/src/Parameter.v
// =========================================================================
// Practical 4: StarCore-1 — Single-Cycle Processor in Verilog
// =========================================================================
//
// GROUP NUMBER: 18
//
// MEMBERS:
//   - Matteo Buxman, BXMMAT001
//   - Emmanuel Basua, BSXEMM001

// File        : Parameter.v
// Description : Shared compile-time parameters used across all modules.
//               Include this file at the top of every .v file:
//                   `include "../src/Parameter.v"
// =============================================================================

`ifndef PARAMETER_H_
`define PARAMETER_H_

// ---------------------------------------------------------------------------
// Memory dimensions
// ---------------------------------------------------------------------------
`define COL     16          // Data/instruction word width (bits)
`define ROW_I   16          // Instruction memory depth (words, 16 x 16-bit)
`define ROW_D    8          // Data memory depth (words,  8 x 16-bit)

// ---------------------------------------------------------------------------
// Simulation control
// Increase SIM_TIME if your test program needs more clock cycles to complete.
// At 10 ns per clock (100 MHz) each #10 is one half-period; 320 ns = 16 cycles.
// ---------------------------------------------------------------------------
`define SIM_TIME  #640      // Total simulation time for integration testbench

// ---------------------------------------------------------------------------
// Output file for data-memory dump (used in DataMemory.v $fmonitor)
// ---------------------------------------------------------------------------
`define DMEM_LOG  "./waves/dmem_log.txt"

`endif  // PARAMETER_H_

Practical-4/src/ControlUnit.v
// =========================================================================
// Practical 4: StarCore-1 — Single-Cycle Processor in Verilog
// =========================================================================
//
// GROUP NUMBER: 18
//
// MEMBERS:
//   - Emmanuel Basua, BSXEMM001
//   - Matteo Buxman, BXMMAT001

// File        : ControlUnit.v
// Description : Main Control Unit.
//               Decodes the 4-bit opcode from the fetched instruction and
//               asserts the full set of control signals that govern the
//               Datapath for the current clock cycle.
//               This is a purely combinational module.
//
// Task 6 — Student Implementation Required
// =============================================================================

`timescale 1ns / 1ps
`include "../src/Parameter.v"

module ControlUnit (
    input  [3:0] opcode,        // Instruction opcode [15:12] from Datapath

    // ALU control
    output reg [1:0] alu_op,    // Passed to ALU_Control: 10=mem, 01=branch, 00=R-type

    // PC control
    output reg       jump,      // Assert to select the jump target PC
    output reg       beq,       // Assert to enable branch-on-equal
    output reg       bne,       // Assert to enable branch-on-not-equal

    // Memory control
    output reg       mem_read,  // Assert to enable data memory read output
    output reg       mem_write, // Assert to write data memory on posedge clk

    // Datapath multiplexer selects
    output reg       alu_src,   // 0 = RS2 register value; 1 = sign-extended immediate
    output reg       reg_dst,   // 0 = instr[8:6] (I-type WS); 1 = instr[5:3] (R-type WS)
    output reg       mem_to_reg,// 0 = ALU result; 1 = data memory read data (for LD)
    output reg       reg_write  // Assert to write the register file on posedge clk
);

    // -------------------------------------------------------------------------
    // Control signal truth table (from Section 3.3 of the manual):
    //
    // Opcode | Instr     | RegDst | ALUSrc | MemToReg | RegWrite | MemRd | MemWr | Branch | ALUOp | Jump
    // -------+-----------+--------+--------+----------+----------+-------+-------+--------+-------+-----
    // 0000   | LD        |   0    |   1    |    1     |    1     |   1   |   0   |   0    |  10   |  0
    // 0001   | ST        |   0    |   1    |    0     |    0     |   0   |   1   |   0    |  10   |  0
    // 0010–  | R-type    |   1    |   0    |    0     |    1     |   0   |   0   |   0    |  00   |  0
    // 1001   | (ADD–SLT) |        |        |          |          |       |       |        |       |
    // 1010   | Reserved  |   0    |   0    |    0     |    0     |   0   |   0   |   0    |  00   |  0
    // 1011   | BEQ       |   0    |   0    |    0     |    0     |   0   |   0   |   1    |  01   |  0
    // 1100   | BNE       |   0    |   0    |    0     |    0     |   0   |   0   |   1    |  01   |  0
    // 1101   | JMP       |   0    |   0    |    0     |    0     |   0   |   0   |   0    |  00   |  1
    //
    // For BEQ and BNE the Branch signal is asserted; the Datapath uses beq & zero_flag
    // and bne & ~zero_flag respectively to determine whether the branch is taken.
    // -------------------------------------------------------------------------

    always @(*) begin

        // Setting everything to 0 first prevents "Latches" and ensures 
        // that undefined opcodes don't accidentally write to memory or registers.
        reg_dst    = 1'b0;
        alu_src    = 1'b0;
        mem_to_reg = 1'b0;
        reg_write  = 1'b0;
        mem_read   = 1'b0;
        mem_write  = 1'b0;
        beq        = 1'b0;
        bne        = 1'b0;
        alu_op     = 2'b00;
        jump       = 1'b0;

        case (opcode)
            4'b0000: begin  // LD (Load Word)
                alu_src    = 1'b1; 
                mem_to_reg = 1'b1; 
                reg_write  = 1'b1; 
                mem_read   = 1'b1; 
                alu_op     = 2'b10;
            end

            4'b0001: begin  // ST (Store Word)
                alu_src    = 1'b1; 
                mem_write  = 1'b1; 
                alu_op     = 2'b10; 
            end

            // R-type instructions (ADD, SUB, INV, SHL, SHR, AND, OR, SLT)
            4'b0010, 4'b0011, 4'b0100, 4'b0101,
            4'b0110, 4'b0111, 4'b1000, 4'b1001: begin 
                reg_dst    = 1'b1; 
                reg_write  = 1'b1; 
                alu_op     = 2'b00; 
            end

            4'b1011: begin  // BEQ (Branch if Equal)
                beq        = 1'b1; 
                alu_op     = 2'b01; 
            end

            4'b1100: begin  // BNE (Branch if Not Equal)
                bne        = 1'b1; 
                alu_op     = 2'b01; 
            end

            4'b1101: begin  // JMP (Jump)
                jump       = 1'b1;  
            end

            default: begin
                // No action needed; defaults are already 0.
            end
        endcase
    end
endmodule

Practical-4/tb/ControlUnit_tb.v
// =============================================================================
// EEE4120F Practical 4 — StarCore-1 Processor
// File        : ControlUnit_tb.v
// Description : Testbench for the Main Control Unit (Task 6).
//               Applies every defined opcode and verifies all ten control
//               signal outputs match the truth table in Section 3.3 of the
//               practical manual.
//
// Run:
//   iverilog -Wall -I ../src -o ../build/cu_sim ../src/ControlUnit.v ControlUnit_tb.v
//   cd ../test && ../build/cu_sim
//   gtkwave ../waves/cu_tb.vcd &
// =============================================================================

`timescale 1ns / 1ps
`include "../src/Parameter.v"

module ControlUnit_tb;

    reg  [3:0] opcode;

    wire [1:0] alu_op;
    wire       jump;
    wire       beq;
    wire       bne;
    wire       mem_read;
    wire       mem_write;
    wire       alu_src;
    wire       reg_dst;
    wire       mem_to_reg;
    wire       reg_write;

    ControlUnit uut (
        .opcode     (opcode),
        .alu_op     (alu_op),
        .jump       (jump),
        .beq        (beq),
        .bne        (bne),
        .mem_read   (mem_read),
        .mem_write  (mem_write),
        .alu_src    (alu_src),
        .reg_dst    (reg_dst),
        .mem_to_reg (mem_to_reg),
        .reg_write  (reg_write)
    );

    initial begin
        $dumpfile("./waves/cu_tb.vcd");
        $dumpvars(0, ControlUnit_tb);
    end

    integer fail_count;
    integer test_id;
    integer i;

    // -------------------------------------------------------------------------
    // Composite check task — verifies all 10 control signals in one call.
    // Parameters mirror the truth table column order from the manual.
    // -------------------------------------------------------------------------
    task check_ctrl;
        // Expected values
        input [1:0] e_alu_op;
        input       e_jump, e_beq, e_bne;
        input       e_mem_read, e_mem_write;
        input       e_alu_src, e_reg_dst;
        input       e_mem_to_reg, e_reg_write;
        input [63:0] id;

        reg failed;
        begin
            failed = 1'b0;

            if (alu_op    !== e_alu_op)    begin $display("  MISMATCH alu_op:    %b vs %b", alu_op,    e_alu_op);    failed=1; end
            if (jump      !== e_jump)      begin $display("  MISMATCH jump:      %b vs %b", jump,      e_jump);      failed=1; end
            if (beq       !== e_beq)       begin $display("  MISMATCH beq:       %b vs %b", beq,       e_beq);       failed=1; end
            if (bne       !== e_bne)       begin $display("  MISMATCH bne:       %b vs %b", bne,       e_bne);       failed=1; end
            if (mem_read  !== e_mem_read)  begin $display("  MISMATCH mem_read:  %b vs %b", mem_read,  e_mem_read);  failed=1; end
            if (mem_write !== e_mem_write) begin $display("  MISMATCH mem_write: %b vs %b", mem_write, e_mem_write); failed=1; end
            if (alu_src   !== e_alu_src)   begin $display("  MISMATCH alu_src:   %b vs %b", alu_src,   e_alu_src);   failed=1; end
            if (reg_dst   !== e_reg_dst)   begin $display("  MISMATCH reg_dst:   %b vs %b", reg_dst,   e_reg_dst);   failed=1; end
            if (mem_to_reg!== e_mem_to_reg)begin $display("  MISMATCH mem_to_reg:%b vs %b", mem_to_reg,e_mem_to_reg);failed=1; end
            if (reg_write !== e_reg_write) begin $display("  MISMATCH reg_write: %b vs %b", reg_write, e_reg_write); failed=1; end

            if (failed) begin
                $display("FAIL [T%0d]: opcode=%b", id, opcode);
                fail_count = fail_count + 1;
            end else
                $display("PASS [T%0d]: opcode=%b all signals correct", id, opcode);
        end
    endtask

    initial begin
        fail_count = 0;
        test_id    = 1;
        $display("=== ControlUnit Testbench ===");
        $display("    Format: check_ctrl(alu_op, jump, beq, bne, mem_read, mem_write, alu_src, reg_dst, mem_to_reg, reg_write, id)");

        // LD (0000)
        opcode = 4'b0000; #10;
        check_ctrl(2'b10, 1'b0, 1'b0, 1'b0, 1'b1, 1'b0, 1'b1, 1'b0, 1'b1, 1'b1, test_id);
        test_id = test_id + 1;

        // ST (0001)
        opcode = 4'b0001; #10;
        check_ctrl(2'b10, 1'b0, 1'b0, 1'b0, 1'b0, 1'b1, 1'b1, 1'b0, 1'b0, 1'b0, test_id);
        test_id = test_id + 1;

        // R-Type 
        // All R-types share the same control signal pattern
        // (alu_op=00, jump=0, beq=0, bne=0, mr=0, mw=0, as=0, rd=1, mtr=0, rw=1)
        for (i = 4'b0010; i <= 4'b1001; i = i + 1) begin
            opcode = i[3:0]; #10;
            check_ctrl(2'b00, 1'b0, 1'b0, 1'b0, 1'b0, 1'b0, 1'b0, 1'b1, 1'b0, 1'b1, test_id);
            test_id = test_id + 1;
        end

        // BEQ (1011)
        opcode = 4'b1011; #10;
        check_ctrl(2'b01, 1'b0, 1'b1, 1'b0, 1'b0, 1'b0, 1'b0, 1'b0, 1'b0, 1'b0, test_id);
        test_id = test_id + 1;

        // BNE (1100)
        opcode = 4'b1100; #10;
        check_ctrl(2'b01, 1'b0, 1'b0, 1'b1, 1'b0, 1'b0, 1'b0, 1'b0, 1'b0, 1'b0, test_id);
        test_id = test_id + 1;

        // JMP (1101)
        opcode = 4'b1101; #10;
        check_ctrl(2'b00, 1'b1, 1'b0, 1'b0, 1'b0, 1'b0, 1'b0, 1'b0, 1'b0, 1'b0, test_id);
        test_id = test_id + 1;

        // Undefined/Reserved
        
        $display("Checking Reserved Opcode (1010):");
        opcode = 4'b1010; #10;
        check_ctrl(2'b00, 1'b0, 1'b0, 1'b0, 1'b0, 1'b0, 1'b0, 1'b0, 1'b0, 1'b0, test_id);
        test_id = test_id + 1;
        
        $display("");
        if (fail_count == 0)
            $display("=== ALL %0d TESTS PASSED ===", test_id - 1);
        else
            $display("=== %0d / %0d TESTS FAILED ===", fail_count, test_id - 1);
        $finish;
    end

endmodule

Practical-4/waves/cu_tb.vcd
$date
	Wed Apr 22 10:17:05 2026
$end
$version
	Icarus Verilog
$end
$timescale
	1ps
$end
$scope module ControlUnit_tb $end
$var wire 1 ! reg_write $end
$var wire 1 " reg_dst $end
$var wire 1 # mem_write $end
$var wire 1 $ mem_to_reg $end
$var wire 1 % mem_read $end
$var wire 1 & jump $end
$var wire 1 ' bne $end
$var wire 1 ( beq $end
$var wire 1 ) alu_src $end
$var wire 2 * alu_op [1:0] $end
$var reg 4 + opcode [3:0] $end
$var integer 32 , fail_count [31:0] $end
$var integer 32 - i [31:0] $end
$var integer 32 . test_id [31:0] $end
$scope module uut $end
$var wire 4 / opcode [3:0] $end
$var reg 2 0 alu_op [1:0] $end
$var reg 1 ) alu_src $end
$var reg 1 ( beq $end
$var reg 1 ' bne $end
$var reg 1 & jump $end
$var reg 1 % mem_read $end
$var reg 1 $ mem_to_reg $end
$var reg 1 # mem_write $end
$var reg 1 " reg_dst $end
$var reg 1 ! reg_write $end
$upscope $end
$scope task check_ctrl $end
$var reg 2 1 e_alu_op [1:0] $end
$var reg 1 2 e_alu_src $end
$var reg 1 3 e_beq $end
$var reg 1 4 e_bne $end
$var reg 1 5 e_jump $end
$var reg 1 6 e_mem_read $end
$var reg 1 7 e_mem_to_reg $end
$var reg 1 8 e_mem_write $end
$var reg 1 9 e_reg_dst $end
$var reg 1 : e_reg_write $end
$var reg 1 ; failed $end
$var reg 64 < id [63:0] $end
$upscope $end
$upscope $end
$enddefinitions $end
$comment Show the parameter values. $end
$dumpall
$end
#0
$dumpvars
bx <
x;
x:
x9
x8
x7
x6
x5
x4
x3
x2
bx 1
b10 0
b0 /
b1 .
bx -
b0 ,
b0 +
b10 *
1)
0(
0'
0&
1%
1$
0#
0"
1!
$end
#10000
1#
b10 *
b10 0
0%
0!
0$
1)
b1 +
b1 /
b10 .
0;
b1 <
1:
17
09
12
08
16
04
03
05
b10 1
#20000
1!
1"
b0 *
b0 0
0#
0)
b10 +
b10 /
b10 -
b11 .
b10 <
0:
07
18
06
#30000
1!
1"
b11 +
b11 /
b11 -
b100 .
b11 <
1:
19
02
08
b0 1
#40000
1!
1"
b100 +
b100 /
b100 -
b101 .
b100 <
#50000
1!
1"
b101 +
b101 /
b101 -
b110 .
b101 <
#60000
1!
1"
b110 +
b110 /
b110 -
b111 .
b110 <
#70000
1!
1"
b111 +
b111 /
b111 -
b1000 .
b111 <
#80000
1!
1"
b1000 +
b1000 /
b1000 -
b1001 .
b1000 <
#90000
1!
1"
b1001 +
b1001 /
b1001 -
b1010 .
b1001 <
#100000
b1 *
b1 0
1(
0!
0"
b1011 +
b1011 /
b1010 -
b1011 .
b1010 <
#110000
1'
b1 *
b1 0
0(
b1100 +
b1100 /
b1100 .
b1011 <
0:
09
13
b1 1
#120000
1&
b0 *
b0 0
0'
b1101 +
b1101 /
b1101 .
b1100 <
14
03
#130000
0&
b1010 +
b1010 /
b1110 .
b1101 <
04
15
b0 1
#140000
b1111 .
b1110 <
05
