Practical-4/src/Parameter.v
// =========================================================================
// Practical 4: StarCore-1 — Single-Cycle Processor in Verilog
// =========================================================================
//
// GROUP NUMBER: 18
//
// MEMBERS:
//   - Matteo Buxman, BXMMAT001
//   - Emmanuel Basua, BSXEMM001

// File        : Parameter.v
// Description : Shared compile-time parameters used across all modules.
//               Include this file at the top of every .v file:
//                   `include "../src/Parameter.v"
// =============================================================================

`ifndef PARAMETER_H_
`define PARAMETER_H_

// ---------------------------------------------------------------------------
// Memory dimensions
// ---------------------------------------------------------------------------
`define COL     16          // Data/instruction word width (bits)
`define ROW_I   16          // Instruction memory depth (words, 16 x 16-bit)
`define ROW_D    8          // Data memory depth (words,  8 x 16-bit)

// ---------------------------------------------------------------------------
// Simulation control
// Increase SIM_TIME if your test program needs more clock cycles to complete.
// At 10 ns per clock (100 MHz) each #10 is one half-period; 320 ns = 16 cycles.
// ---------------------------------------------------------------------------
`define SIM_TIME  #640      // Total simulation time for integration testbench

// ---------------------------------------------------------------------------
// Output file for data-memory dump (used in DataMemory.v $fmonitor)
// ---------------------------------------------------------------------------
`define DMEM_LOG  "./waves/dmem_log.txt"

`endif  // PARAMETER_H_

Practical-4/src/DataMemory.v
// =========================================================================
// Practical 4: StarCore-1 — Single-Cycle Processor in Verilog
// =========================================================================
//
// GROUP NUMBER: 18
//
// MEMBERS:
//   - Matteo Buxman, BXMMAT001
//   - Emmanuel Basua, BSXEMM001

// File        : DataMemory.v
// Description : Data Memory (RAM).
//               8 words × 16 bits. Contents loaded at simulation start from
//               the binary file ./test/test.data using $readmemb.
//               Writes are synchronous (positive-edge clocked).
//               Reads are combinational and gated by the mem_read enable.
//
// Task 4 — Student Implementation Required
// =============================================================================

`timescale 1ns / 1ps
`include "../src/Parameter.v"

module DataMemory (
    input        clk,

    // Shared address bus (used for both reads and writes)
    input  [15:0] mem_access_addr,  // Byte address; only lower bits used for indexing

    // Write port
    input  [15:0] mem_write_data,   // Data to store
    input        mem_write_en,      // Assert to write on the next posedge clk

    // Read port
    input        mem_read,          // Assert to enable the read output
    output [15:0] mem_read_data     // Read result; 16'd0 when mem_read is de-asserted
);

    reg [`COL-1:0] memory [`ROW_D-1:0];

    wire [2:0] ram_addr = mem_access_addr[2:0];

    integer log_fd;
    initial begin
        $readmemb("./test/test.data", memory);
    end

    initial begin
        log_fd = $fopen(`DMEM_LOG);
        `SIM_TIME;
        $fclose(log_fd);
    end

    always @(posedge clk) begin
        if (mem_write_en)
            memory[ram_addr] <= mem_write_data;
        $fdisplay(log_fd, "t=%0t  [0]=%h [1]=%h [2]=%h [3]=%h",
                  $time, memory[0], memory[1], memory[2], memory[3]);
    end

    assign mem_read_data = mem_read ? memory[ram_addr] : 16'd0;

endmodule

Practical-4/tb/DataMemory_tb.v
// =============================================================================
// EEE4120F Practical 4 — StarCore-1 Processor
// File        : DataMemory_tb.v
// Description : Testbench for the Data Memory module (Task 4).
//               Verifies synchronous write, gated combinational read,
//               write followed by immediate read, and disabled-write safety.
//
// Run:
//   iverilog -Wall -I ../src -o ../build/dm_sim ../src/DataMemory.v DataMemory_tb.v
//   cd ../test && ../build/dm_sim
//   gtkwave ../waves/dm_tb.vcd &
// =============================================================================

`timescale 1ns / 1ps
`include "../src/Parameter.v"

module DataMemory_tb;

    reg        clk;
    reg  [15:0] mem_access_addr;
    reg  [15:0] mem_write_data;
    reg        mem_write_en;
    reg        mem_read;
    wire [15:0] mem_read_data;

    DataMemory uut (
        .clk             (clk),
        .mem_access_addr (mem_access_addr),
        .mem_write_data  (mem_write_data),
        .mem_write_en    (mem_write_en),
        .mem_read        (mem_read),
        .mem_read_data   (mem_read_data)
    );

    initial clk = 1'b0;
    always  #5 clk = ~clk;

    initial begin
        $dumpfile("./waves/dm_tb.vcd");
        $dumpvars(0, DataMemory_tb);
    end

    integer fail_count;
    integer test_id;
    integer i;

    // Expected initial contents from test.data
    reg [15:0] init_data [0:7];

    task check16;
        input [15:0] got;
        input [15:0] expected;
        input [63:0] id;
        begin
            if (got !== expected) begin
                $display("FAIL [T%0d]: got = 0x%h, expected = 0x%h", id, got, expected);
                fail_count = fail_count + 1;
            end else
                $display("PASS [T%0d]: value = 0x%h", id, got);
        end
    endtask

    initial begin
        fail_count      = 0;
        test_id         = 1;
        mem_write_en    = 1'b0;
        mem_read        = 1'b0;
        mem_access_addr = 16'd0;
        mem_write_data  = 16'd0;

        init_data[0] = 16'h0001;
        init_data[1] = 16'h0002;
        init_data[2] = 16'h0003;
        init_data[3] = 16'h0004;
        init_data[4] = 16'h0005;
        init_data[5] = 16'h0006;
        init_data[6] = 16'h0007;
        init_data[7] = 16'h0008;

        $display("=== DataMemory Testbench ===");

        // Wait a clock edge so $readmemb has taken effect and the sim is stable
        @(posedge clk); #1;

        // ------------------------------------------------------------------
        // TEST GROUP 1: Read back initial values loaded from test.data
        // ------------------------------------------------------------------
        $display("--- Group 1: Verify $readmemb initialisation ---");

        mem_read = 1'b1;
        for (i = 0; i < 8; i = i + 1) begin
            mem_access_addr = i[15:0]; #2;
            check16(mem_read_data, init_data[i], test_id);
            test_id = test_id + 1;
        end

        // ------------------------------------------------------------------
        // TEST GROUP 2: Write new values to all 8 locations, then read back
        // ------------------------------------------------------------------
        $display("--- Group 2: Write then read all 8 locations ---");

        for (i = 0; i < 8; i = i + 1) begin
            mem_read        = 1'b0;
            mem_write_en    = 1'b1;
            mem_access_addr = i[15:0];
            mem_write_data  = 16'hA000 + i[15:0];
            @(posedge clk); #1;
            mem_write_en    = 1'b0;

            mem_read        = 1'b1;
            mem_access_addr = i[15:0]; #2;
            check16(mem_read_data, 16'hA000 + i[15:0], test_id);
            test_id = test_id + 1;
        end

        // ------------------------------------------------------------------
        // TEST GROUP 3: mem_read = 0 must produce 16'd0 output
        // ------------------------------------------------------------------
        $display("--- Group 3: mem_read disabled -> output must be 0 ---");

        mem_read        = 1'b0;
        mem_access_addr = 16'd0; #2;
        check16(mem_read_data, 16'd0, test_id); test_id = test_id + 1;

        mem_access_addr = 16'd5; #2;
        check16(mem_read_data, 16'd0, test_id); test_id = test_id + 1;

        // ------------------------------------------------------------------
        // TEST GROUP 4: Write then immediately read on the next cycle
        // ------------------------------------------------------------------
        $display("--- Group 4: Write followed by immediate read ---");

        mem_write_en    = 1'b1;
        mem_access_addr = 16'd3;
        mem_write_data  = 16'hBEEF;
        @(posedge clk); #1;
        mem_write_en    = 1'b0;

        mem_read        = 1'b1;
        mem_access_addr = 16'd3; #2;
        check16(mem_read_data, 16'hBEEF, test_id); test_id = test_id + 1;

        // ------------------------------------------------------------------
        // TEST GROUP 5: Disabled write must not alter memory
        // ------------------------------------------------------------------
        $display("--- Group 5: mem_write_en=0 must not overwrite memory ---");

        mem_write_en    = 1'b0;
        mem_access_addr = 16'd3;
        mem_write_data  = 16'hDEAD;
        @(posedge clk); #1;

        mem_read        = 1'b1;
        mem_access_addr = 16'd3; #2;
        check16(mem_read_data, 16'hBEEF, test_id); test_id = test_id + 1;

        $display("");
        if (fail_count == 0)
            $display("=== ALL %0d TESTS PASSED ===", test_id - 1);
        else
            $display("=== %0d / %0d TESTS FAILED ===", fail_count, test_id - 1);
        $finish;
    end

endmodule

Practical-4/waves/dm_tb.vcd
$date
	Wed Apr 22 10:16:46 2026
$end
$version
	Icarus Verilog
$end
$timescale
	1ps
$end
$scope module DataMemory_tb $end
$var wire 16 ! mem_read_data [15:0] $end
$var reg 1 " clk $end
$var reg 16 # mem_access_addr [15:0] $end
$var reg 1 $ mem_read $end
$var reg 16 % mem_write_data [15:0] $end
$var reg 1 & mem_write_en $end
$var integer 32 ' fail_count [31:0] $end
$var integer 32 ( i [31:0] $end
$var integer 32 ) test_id [31:0] $end
$scope module uut $end
$var wire 1 " clk $end
$var wire 16 * mem_access_addr [15:0] $end
$var wire 1 $ mem_read $end
$var wire 16 + mem_write_data [15:0] $end
$var wire 1 & mem_write_en $end
$var wire 3 , ram_addr [2:0] $end
$var wire 16 - mem_read_data [15:0] $end
$var integer 32 . log_fd [31:0] $end
$upscope $end
$scope task check16 $end
$var reg 16 / expected [15:0] $end
$var reg 16 0 got [15:0] $end
$var reg 64 1 id [63:0] $end
$upscope $end
$upscope $end
$enddefinitions $end
$comment Show the parameter values. $end
$dumpall
$end
#0
$dumpvars
bx 1
bx 0
bx /
b10 .
b0 -
b0 ,
b0 +
b0 *
b1 )
bx (
b0 '
0&
b0 %
0$
b0 #
0"
b0 !
$end
#5000
1"
#6000
b1 !
b1 -
b0 (
1$
#8000
b10 !
b10 -
b1 ,
b1 #
b1 *
b1 (
b10 )
b1 1
b1 /
b1 0
#10000
b11 !
b11 -
b10 ,
b10 #
b10 *
b10 (
b11 )
b10 1
b10 /
b10 0
0"
#12000
b100 !
b100 -
b11 ,
b11 #
b11 *
b11 (
b100 )
b11 1
b11 /
b11 0
#14000
b101 !
b101 -
b100 ,
b100 #
b100 *
b100 (
b101 )
b100 1
b100 /
b100 0
#15000
1"
#16000
b110 !
b110 -
b101 ,
b101 #
b101 *
b101 (
b110 )
b101 1
b101 /
b101 0
#18000
b111 !
b111 -
b110 ,
b110 #
b110 *
b110 (
b111 )
b110 1
b110 /
b110 0
#20000
b1000 !
b1000 -
b111 ,
b111 #
b111 *
b111 (
b1000 )
b111 1
b111 /
b111 0
0"
#22000
b0 ,
b0 !
b0 -
b1010000000000000 %
b1010000000000000 +
b0 #
b0 *
1&
0$
b0 (
b1001 )
b1000 1
b1000 /
b1000 0
#25000
1"
#26000
b1010000000000000 !
b1010000000000000 -
1$
0&
#28000
b1 ,
b0 !
b0 -
b1010000000000001 %
b1010000000000001 +
b1 #
b1 *
1&
0$
b1 (
b1010 )
b1001 1
b1010000000000000 /
b1010000000000000 0
#30000
0"
#35000
1"
#36000
b1010000000000001 !
b1010000000000001 -
1$
0&
#38000
b10 ,
b0 !
b0 -
b1010000000000010 %
b1010000000000010 +
b10 #
b10 *
1&
0$
b10 (
b1011 )
b1010 1
b1010000000000001 /
b1010000000000001 0
#40000
0"
#45000
1"
#46000
b1010000000000010 !
b1010000000000010 -
1$
0&
#48000
b11 ,
b0 !
b0 -
b1010000000000011 %
b1010000000000011 +
b11 #
b11 *
1&
0$
b11 (
b1100 )
b1011 1
b1010000000000010 /
b1010000000000010 0
#50000
0"
#55000
1"
#56000
b1010000000000011 !
b1010000000000011 -
1$
0&
#58000
b100 ,
b0 !
b0 -
b1010000000000100 %
b1010000000000100 +
b100 #
b100 *
1&
0$
b100 (
b1101 )
b1100 1
b1010000000000011 /
b1010000000000011 0
#60000
0"
#65000
1"
#66000
b1010000000000100 !
b1010000000000100 -
1$
0&
#68000
b101 ,
b0 !
b0 -
b1010000000000101 %
b1010000000000101 +
b101 #
b101 *
1&
0$
b101 (
b1110 )
b1101 1
b1010000000000100 /
b1010000000000100 0
#70000
0"
#75000
1"
#76000
b1010000000000101 !
b1010000000000101 -
1$
0&
#78000
b110 ,
b0 !
b0 -
b1010000000000110 %
b1010000000000110 +
b110 #
b110 *
1&
0$
b110 (
b1111 )
b1110 1
b1010000000000101 /
b1010000000000101 0
#80000
0"
#85000
1"
#86000
b1010000000000110 !
b1010000000000110 -
1$
0&
#88000
b111 ,
b0 !
b0 -
b1010000000000111 %
b1010000000000111 +
b111 #
b111 *
1&
0$
b111 (
b10000 )
b1111 1
b1010000000000110 /
b1010000000000110 0
#90000
0"
#95000
1"
#96000
b1010000000000111 !
b1010000000000111 -
1$
0&
#98000
b0 ,
b0 !
b0 -
b0 #
b0 *
0$
b1000 (
b10001 )
b10000 1
b1010000000000111 /
b1010000000000111 0
#100000
b101 ,
b101 #
b101 *
b10010 )
b10001 1
b0 /
b0 0
0"
#102000
b11 ,
b1011111011101111 %
b1011111011101111 +
b11 #
b11 *
1&
b10011 )
b10010 1
#105000
1"
#106000
b1011111011101111 !
b1011111011101111 -
1$
0&
#108000
b1101111010101101 %
b1101111010101101 +
b10100 )
b10011 1
b1011111011101111 /
b1011111011101111 0
#110000
0"
#115000
1"
#118000
b10101 )
b10100 1
